setup.cfg
setup.py
didyoumean/__init__.py
didyoumean/didyoumean_api_tests.py
didyoumean/didyoumean_common_tests.py
didyoumean/didyoumean_contextmanager.py
didyoumean/didyoumean_decorator.py
didyoumean/didyoumean_hook.py
didyoumean/didyoumean_internal.py
didyoumean/didyoumean_internal_tests.py
didyoumean/didyoumean_postmortem.py
didyoumean/didyoumean_re.py
didyoumean/didyoumean_re_tests.py
didyoumean/didyoumean_sugg_tests.py
didyoumean/readme_examples.py
didyoumean_suggestions.egg-info/PKG-INFO
didyoumean_suggestions.egg-info/SOURCES.txt
didyoumean_suggestions.egg-info/dependency_links.txt
didyoumean_suggestions.egg-info/top_level.txt