Metadata-Version: 1.1
Name: didyoumean-suggestions
Version: 0.3
Summary: Logic to have suggestions in case of errors (NameError, AttributeError, ImportError, TypeError, etc).
Home-page: https://github.com/SylvainDe/DidYouMean-Python
Author: Sylvain Desodt
Author-email: sylvain.desodt+didyoumean@gmail.com
License: UNKNOWN
Download-URL: https://github.com/SylvainDe/DidYouMean-Python/tarball/0.1
Keywords: didyoumean,exception,error,suggestion,excepthook,decorator,contextmanager,typo
Platform: UNKNOWN
